pycooltext/__init__.py
pycooltext/chars.py
pycooltext/core.py
pycooltext-0.0.1.dist-info/METADATA
pycooltext-0.0.1.dist-info/WHEEL
pycooltext-0.0.1.dist-info/top_level.txt
pycooltext-0.0.1.dist-info/RECORD
