Metadata-Version: 2.1
Name: pycooltext
Version: 0.0.1
Summary: A function to print cool text.
Author: Hart Traveller
Author-email: hart@cephalon.io
Requires-Dist: rich
Requires-Dist: pathlib
